rewind_reward_pytorch/__init__.py
rewind_reward_pytorch/rewind_reward.py
rewind_reward_pytorch-0.0.25.dist-info/METADATA
rewind_reward_pytorch-0.0.25.dist-info/WHEEL
rewind_reward_pytorch-0.0.25.dist-info/licenses/LICENSE
rewind_reward_pytorch-0.0.25.dist-info/RECORD
