Metadata-Version: 2.4
Name: rewind-reward-pytorch
Version: 0.0.25
Summary: Rewind Reward
Project-URL: Homepage, https://pypi.org/project/rewind-reward-pytorch/
Project-URL: Repository, https://github.com/lucidrains/rewind-reward-pytorch
Author-email: Phil Wang <lucidrains@gmail.com>
License: MIT License
License-File: LICENSE
Keywords: artificial intelligence,deep learning,robotics
Classifier: Development Status :: 4 - Beta
Classifier: Intended Audience :: Developers
Classifier: License :: OSI Approved :: MIT License
Classifier: Programming Language :: Python :: 3.9
Classifier: Topic :: Scientific/Engineering :: Artificial Intelligence
Requires-Python: >=3.9
Requires-Dist: einops>=0.8.1
Requires-Dist: einx>=0.3.0
Requires-Dist: hl-gauss-pytorch>=0.1.24
Requires-Dist: sentence-transformers
Requires-Dist: torch>=2.4
Requires-Dist: transformers
Requires-Dist: vit-pytorch
Requires-Dist: x-mlps-pytorch>=0.0.25
Requires-Dist: x-transformers
Provides-Extra: examples
Provides-Extra: test
Requires-Dist: pytest; extra == 'test'
